dbt/__init__.py
dbt/adapters/synapse/__init__.py
dbt/adapters/synapse/__version__.py
dbt/adapters/synapse/synapse_adapter.py
dbt/adapters/synapse/synapse_column.py
dbt/adapters/synapse/synapse_connection_manager.py
dbt/adapters/synapse/synapse_credentials.py
dbt/adapters/synapse/synapse_relation.py
dbt/adapters/synapse/relation_configs/__init__.py
dbt/adapters/synapse/relation_configs/base.py
dbt/adapters/synapse/relation_configs/policies.py
dbt/include/synapse/__init__.py
dbt/include/synapse/dbt_project.yml
dbt/include/synapse/macros/adapters/catalog.sql
dbt/include/synapse/macros/adapters/columns.sql
dbt/include/synapse/macros/adapters/indexes.sql
dbt/include/synapse/macros/adapters/metadata.sql
dbt/include/synapse/macros/adapters/persist_docs.sql
dbt/include/synapse/macros/adapters/relation.sql
dbt/include/synapse/macros/adapters/replace.sql
dbt/include/synapse/macros/adapters/schema.sql
dbt/include/synapse/macros/adapters/show.sql
dbt/include/synapse/macros/materializations/models/materialized_view/create_materialized_view_as.sql
dbt/include/synapse/macros/materializations/models/materialized_view/materialized_view.sql
dbt/include/synapse/macros/materializations/models/table/create_table_as.sql
dbt/include/synapse/macros/materializations/models/table/create_table_constraints.sql
dbt/include/synapse/macros/materializations/models/view/create_view_as.sql
dbt/include/synapse/macros/materializations/seeds/helpers.sql
dbt/include/synapse/macros/materializations/seeds/str_replace.sql
dbt/include/synapse/macros/materializations/snapshots/snapshot.sql
dbt/include/synapse/macros/materializations/tests/helpers.sql
dbt/include/synapse/macros/materializations/tests/test.sql
dbt/include/synapse/macros/utils/date_spine.sql
dbt/include/synapse/macros/utils/generate_series.sql
dbt/include/synapse/macros/utils/split_part.sql
dbt_synapse-1.8.4.dist-info/LICENSE
dbt_synapse-1.8.4.dist-info/METADATA
dbt_synapse-1.8.4.dist-info/WHEEL
dbt_synapse-1.8.4.dist-info/top_level.txt
dbt_synapse-1.8.4.dist-info/RECORD
