Metadata-Version: 2.1
Name: dbt-synapse
Version: 1.8.4
Summary: An Azure Synapse adapter plugin for dbt
Home-page: https://github.com/microsoft/dbt-synapse
Author: Pradeep Srikakolapu, Nandan Hegde, Chaerin Lee, Alieu Sanneh, Anders Swanson, Sam Debruyn
License: MIT
Platform: UNKNOWN
Classifier: Development Status :: 5 - Production/Stable
Classifier: License :: OSI Approved :: MIT License
Classifier: Operating System :: Microsoft :: Windows
Classifier: Operating System :: MacOS :: MacOS X
Classifier: Operating System :: POSIX :: Linux
Classifier: Programming Language :: Python :: 3.8
Classifier: Programming Language :: Python :: 3.9
Classifier: Programming Language :: Python :: 3.10
Classifier: Programming Language :: Python :: 3.11
License-File: LICENSE
Requires-Dist: dbt-fabric <1.9.6,>=1.8.0
